odoo8_addon_web_listview_custom_column-8.0.1.0.0.99.dev1-py2.7-nspkg.pth
odoo8_addon_web_listview_custom_column-8.0.1.0.0.99.dev1.dist-info/METADATA
odoo8_addon_web_listview_custom_column-8.0.1.0.0.99.dev1.dist-info/RECORD
odoo8_addon_web_listview_custom_column-8.0.1.0.0.99.dev1.dist-info/WHEEL
odoo8_addon_web_listview_custom_column-8.0.1.0.0.99.dev1.dist-info/namespace_packages.txt
odoo8_addon_web_listview_custom_column-8.0.1.0.0.99.dev1.dist-info/top_level.txt
odoo_addons/web_listview_custom_column/README.rst
odoo_addons/web_listview_custom_column/__init__.py
odoo_addons/web_listview_custom_column/__openerp__.py
odoo_addons/web_listview_custom_column/i18n/web_listview_custom_column.pot
odoo_addons/web_listview_custom_column/models/__init__.py
odoo_addons/web_listview_custom_column/models/ir_ui_view.py
odoo_addons/web_listview_custom_column/security/ir.model.access.csv
odoo_addons/web_listview_custom_column/security/res_groups.xml
odoo_addons/web_listview_custom_column/static/description/icon.png
odoo_addons/web_listview_custom_column/static/src/css/web_listview_custom_column.css
odoo_addons/web_listview_custom_column/static/src/js/web_listview_custom_column.js
odoo_addons/web_listview_custom_column/static/src/xml/web_listview_custom_column.xml
odoo_addons/web_listview_custom_column/tests/__init__.py
odoo_addons/web_listview_custom_column/tests/test_web_listview_custom_column.py
odoo_addons/web_listview_custom_column/views/templates.xml
